embedml/__init__.py
embedml/nn.py
embedml/tensor.py
embedml/util.py
embedml-0.1.3.dist-info/LICENSE
embedml-0.1.3.dist-info/METADATA
embedml-0.1.3.dist-info/WHEEL
embedml-0.1.3.dist-info/top_level.txt
embedml-0.1.3.dist-info/RECORD
