Metadata-Version: 2.1
Name: embedml
Version: 0.1.3
Summary: Minimal autograd engine using numpy with minimal implementation of pyTorch or Jax like library for traning NNs.
Home-page: https://github.com/amirhm/embedml
Author: amirhm
Author-email: amirhm@gmail.com
License: MIT,
Platform: UNKNOWN
Classifier: License :: OSI Approved :: MIT License
Classifier: Programming Language :: Python :: 3
Classifier: Programming Language :: Python :: 3 :: Only
Classifier: Programming Language :: Python :: 3.8
Requires-Python: >=3.7.1
Requires-Dist: numpy
